llmcaller/__init__.py
llmcaller/client.py
llmcaller/exceptions.py
llmcaller/types.py
llmcaller-1.0.0.dist-info/METADATA
llmcaller-1.0.0.dist-info/WHEEL
llmcaller-1.0.0.dist-info/top_level.txt
llmcaller-1.0.0.dist-info/RECORD
