Metadata-Version: 2.1
Name: llmcaller
Version: 1.0.0
Summary: Python SDK for LLMCaller - A unified interface for LLM providers
Author: 
Author-email: 
Classifier: Development Status :: 4 - Beta
Classifier: Intended Audience :: Developers
Classifier: License :: OSI Approved :: MIT License
Classifier: Programming Language :: Python :: 3
Classifier: Programming Language :: Python :: 3.7
Classifier: Programming Language :: Python :: 3.8
Classifier: Programming Language :: Python :: 3.9
Classifier: Programming Language :: Python :: 3.10
Classifier: Programming Language :: Python :: 3.11
Requires-Python: >=3.7
Requires-Dist: aiohttp>=3.8.0
Requires-Dist: requests>=2.28.0
Requires-Dist: sseclient-py>=1.7.2
Requires-Dist: typing_extensions>=4.5.0
